{"cameraMode":{"drawMode":0,"name":"Shaded","section":"Shading Mode"},"sceneLighting":false,"audioPlay":false,"sceneViewState":{"m_AlwaysRefresh":false,"showFog":true,"showSkybox":false,"showFlares":true,"showImageEffects":true,"showParticleSystems":true,"showVisualEffectGraphs":true,"m_FxEnabled":true},"in2DMode":false,"pivot":{"x":0.0,"y":0.5,"z":2.5169999599456789},"rotation":{"x":0.17195190489292146,"y":-0.0014818066265434027,"z":0.000258839427260682,"w":0.9851098656654358},"size":8.003905296325684,"orthographic":false}